setup.py
pyaddr/__init__.py
pyaddr/pyaddr.py
pyaddr.egg-info/PKG-INFO
pyaddr.egg-info/SOURCES.txt
pyaddr.egg-info/dependency_links.txt
pyaddr.egg-info/top_level.txt