Metadata-Version: 1.0
Name: pyaddr
Version: 1.0.2
Summary: extract address from text
Home-page: UNKNOWN
Author: Gary Wang
Author-email: UNKNOWN
License: UNKNOWN
Platform: UNKNOWN
